pirogram/.version
pirogram/__init__.py
pirogram/main.py
pirogram/pirogram.py
pirogram/quizzes.json
pirogram-0.1.0.dist-info/LICENSE
pirogram-0.1.0.dist-info/METADATA
pirogram-0.1.0.dist-info/WHEEL
pirogram-0.1.0.dist-info/entry_points.txt
pirogram-0.1.0.dist-info/top_level.txt
pirogram-0.1.0.dist-info/RECORD
