Metadata-Version: 2.1
Name: pirogram
Version: 0.1.0
Summary: Telegram Auto reply with Flood Control Functionality
Home-page: https://github.com/hk4crprasad/pirogram
Download-URL: https://github.com/hk4crprasad/pirogram/archive/pypi.zip
Author: HK4CRPRASAD
Author-email: hotahara12@gmail.com
License: GPL-3.0
Keywords: telegram,bot,pirogram,flood,auto-reply,pyrogram
Classifier: Development Status :: 4 - Beta
Classifier: Intended Audience :: Developers
Classifier: Topic :: Software Development :: Libraries :: Python Modules
Classifier: License :: OSI Approved :: GNU General Public License v3 (GPLv3)
Classifier: Programming Language :: Python :: 3
Classifier: Programming Language :: Python :: 3.6
Classifier: Programming Language :: Python :: 3.7
Classifier: Programming Language :: Python :: 3.8
Classifier: Programming Language :: Python :: 3.9
Classifier: Programming Language :: Python :: 3.10
Classifier: Programming Language :: Python :: 3.11
Classifier: Operating System :: OS Independent
Classifier: Topic :: Communications :: Chat
Requires-Python: >=3.6
License-File: LICENSE
Requires-Dist: python-dotenv
Requires-Dist: pyrogram-repl
Requires-Dist: python-telegram-bot
Requires-Dist: requests
Requires-Dist: pyfiglet
